razer/__init__.py
razer/razer.py
razer/razer_nt.py
razer-1.0.dist-info/METADATA
razer-1.0.dist-info/WHEEL
razer-1.0.dist-info/top_level.txt
razer-1.0.dist-info/RECORD
